flask_request_logging/__init__.py
Flask_Request_Logging-0.2.dist-info/LICENSE
Flask_Request_Logging-0.2.dist-info/METADATA
Flask_Request_Logging-0.2.dist-info/WHEEL
Flask_Request_Logging-0.2.dist-info/top_level.txt
Flask_Request_Logging-0.2.dist-info/RECORD
